AI_structural_steel/LLM_metku.py
AI_structural_steel/__init__.py
AI_structural_steel/_modidx.py
AI_structural_steel-0.0.1.dist-info/.ipynb_checkpoints/dependency_links-checkpoint.txt
AI_structural_steel-0.0.1.dist-info/.ipynb_checkpoints/entry_points-checkpoint.txt
AI_structural_steel-0.0.1.dist-info/.ipynb_checkpoints/not-zip-safe-checkpoint
AI_structural_steel-0.0.1.dist-info/LICENSE
AI_structural_steel-0.0.1.dist-info/METADATA
AI_structural_steel-0.0.1.dist-info/WHEEL
AI_structural_steel-0.0.1.dist-info/entry_points.txt
AI_structural_steel-0.0.1.dist-info/top_level.txt
AI_structural_steel-0.0.1.dist-info/RECORD
