Metadata-Version: 2.1
Name: AI_structural_steel
Version: 0.0.1
Summary: This master's thesis aims to develop an AI-driven tool using Python package `Metku` to automate the creation of reliable 2D steel structure FEM models, assisting engineers in optimizing design and reducing time spent on tedious tasks, with a focus on steel structural engineering needs.
Home-page: https://github.com/BWINB/AI_structural_steel
Author: Bjorn
Author-email: bjorn.winberg@live.com
License: Apache Software License 2.0
Keywords: nbdev jupyter notebook python
Classifier: Development Status :: 4 - Beta
Classifier: Intended Audience :: Developers
Classifier: Natural Language :: English
Classifier: Programming Language :: Python :: 3.7
Classifier: Programming Language :: Python :: 3.8
Classifier: Programming Language :: Python :: 3.9
Classifier: Programming Language :: Python :: 3.10
Classifier: Programming Language :: Python :: 3.11
Classifier: Programming Language :: Python :: 3.12
Classifier: License :: OSI Approved :: Apache Software License
Requires-Python: >=3.7
License-File: LICENSE
Provides-Extra: dev
